pyrtex/__init__.py
pyrtex/client.py
pyrtex/config.py
pyrtex/exceptions.py
pyrtex/models.py
pyrtex-0.2.7.dist-info/licenses/LICENSE
pyrtex-0.2.7.dist-info/METADATA
pyrtex-0.2.7.dist-info/WHEEL
pyrtex-0.2.7.dist-info/top_level.txt
pyrtex-0.2.7.dist-info/RECORD
