Metadata-Version: 2.4
Name: pyrtex
Version: 0.2.7
Summary: A Python library for batch text extraction and processing using Google Cloud Vertex AI
Author-email: CaptainTrojan <your-email@example.com>
License: MIT
Project-URL: Homepage, https://github.com/CaptainTrojan/pyrtex
Project-URL: Repository, https://github.com/CaptainTrojan/pyrtex
Project-URL: Issues, https://github.com/CaptainTrojan/pyrtex/issues
Project-URL: Documentation, https://github.com/CaptainTrojan/pyrtex#readme
Project-URL: Changelog, https://github.com/CaptainTrojan/pyrtex/releases
Keywords: ai,vertex-ai,google-cloud,text-extraction,batch-processing,gemini,pydantic
Classifier: Development Status :: 3 - Alpha
Classifier: Intended Audience :: Developers
Classifier: License :: OSI Approved :: MIT License
Classifier: Programming Language :: Python :: 3
Classifier: Programming Language :: Python :: 3.9
Classifier: Programming Language :: Python :: 3.10
Classifier: Programming Language :: Python :: 3.11
Classifier: Programming Language :: Python :: 3.12
Requires-Python: >=3.9
License-File: LICENSE
Requires-Dist: pydantic>=2.0.0
Requires-Dist: pydantic-settings>=2.0.0
Requires-Dist: jinja2>=3.0.0
Requires-Dist: google-cloud-aiplatform>=1.40.0
Requires-Dist: google-cloud-storage>=2.10.0
Requires-Dist: google-cloud-bigquery>=3.11.0
Provides-Extra: dev
Requires-Dist: pytest>=7.0.0; extra == "dev"
Requires-Dist: pytest-mock>=3.10.0; extra == "dev"
Requires-Dist: pytest-cov>=4.0.0; extra == "dev"
Requires-Dist: black>=23.0.0; extra == "dev"
Requires-Dist: isort>=5.12.0; extra == "dev"
Requires-Dist: flake8>=6.0.0; extra == "dev"
Requires-Dist: bump2version>=1.0.0; extra == "dev"
Requires-Dist: build>=0.10.0; extra == "dev"
Requires-Dist: twine>=4.0.0; extra == "dev"
Dynamic: license-file
